{
    "format_version": "1.18.0",
    "minecraft:client_entity": {
        "description": {
            "identifier": "tcmb:notch_power",
            "materials": {
                "default": "skeleton"
            },
            "textures": {
                "default":"textures/entity/null"
            },
            "geometry": {
                "default": "geometry.null"
            },
            "render_controllers": [ 
                "controller.render.default" 
            ],
            "spawn_egg": {
                "texture": "tcmb_notch_power",
                "texture_index": 0
            }
        }
    }
}